modules/__init__.py
modules/src/__init__.py
modules/src/authentication_class.py
modules/src/base_class.py
modules/src/id_generator_class.py
modules/src/slugify_class.py
modules/src/user_class.py
modules/src/verification_class.py
tests/__init__.py
tests/module_test.py
afrinet_system-0.0.1.dist-info/METADATA
afrinet_system-0.0.1.dist-info/WHEEL
afrinet_system-0.0.1.dist-info/entry_points.txt
afrinet_system-0.0.1.dist-info/top_level.txt
afrinet_system-0.0.1.dist-info/RECORD
